manos/__init__.py
manos/__main__.py
manos/builtin.py
manos/doxygen.py
manos/option.py
manos/ordered_set.py
manos/roff.py
manos/sentence.py
manos-0.5.0.data/data/man/man1/manos.1
manos-0.5.0.dist-info/licenses/LICENSE
manos-0.5.0.dist-info/METADATA
manos-0.5.0.dist-info/WHEEL
manos-0.5.0.dist-info/entry_points.txt
manos-0.5.0.dist-info/top_level.txt
manos-0.5.0.dist-info/RECORD
