Metadata-Version: 2.4
Name: manos
Version: 0.5.0
Summary: Generate man pages for C projects using Doxygen.
License: GPL v3.0
Project-URL: Source, https://github.com/hgs3/manos.git
Project-URL: Changelog, https://github.com/hgs3/manos/blob/master/CHANGELOG.md
Classifier: Intended Audience :: Developers
Classifier: License :: OSI Approved :: GNU General Public License v3 (GPLv3)
Classifier: Programming Language :: Python
Classifier: Programming Language :: Python :: 3.10
Classifier: Programming Language :: Python :: 3.11
Classifier: Programming Language :: Python :: 3.12
Classifier: Programming Language :: Python :: Implementation :: CPython
Classifier: Topic :: Documentation
Requires-Python: >=3.10
License-File: LICENSE
Requires-Dist: lxml==5.0.0
Requires-Dist: lxml-stubs==0.5.1
Dynamic: license-file
